cbapi/__init__.py
cbapi/auth.py
cbapi/connection.py
cbapi/defense.py
cbapi/errors.py
cbapi/event.py
cbapi/example_helpers.py
cbapi/live_response_api.py
cbapi/models.py
cbapi/oldmodels.py
cbapi/query.py
cbapi/six.py
cbapi/utils.py
cbapi/winerror.py
cbapi/cache/__init__.py
cbapi/cache/lru.py
cbapi/cache/redis.py
cbapi/protection/__init__.py
cbapi/protection/models.py
cbapi/protection/rest_api.py
cbapi/protection/models/connector.yaml
cbapi/protection/models/fileRule.yaml
cbapi/protection/models/notification.yaml
cbapi/protection/models/policy.yaml
cbapi/protection/models/trustedUser.yaml
cbapi/protection/models/user.yaml
cbapi/protection/models/userGroup.yaml
cbapi/psc/__init__.py
cbapi/psc/alerts_query.py
cbapi/psc/base_query.py
cbapi/psc/cblr.py
cbapi/psc/devices_query.py
cbapi/psc/models.py
cbapi/psc/rest_api.py
cbapi/psc/defense/__init__.py
cbapi/psc/defense/models.py
cbapi/psc/defense/rest_api.py
cbapi/psc/defense/models/deviceInfo.yaml
cbapi/psc/defense/models/policyInfo.yaml
cbapi/psc/livequery/__init__.py
cbapi/psc/livequery/models.py
cbapi/psc/livequery/query.py
cbapi/psc/livequery/rest_api.py
cbapi/psc/livequery/models/device_summary.yaml
cbapi/psc/livequery/models/facet.yaml
cbapi/psc/livequery/models/result.yaml
cbapi/psc/livequery/models/run.yaml
cbapi/psc/models/base_alert.yaml
cbapi/psc/models/device.yaml
cbapi/psc/models/workflow.yaml
cbapi/psc/models/workflow_status.yaml
cbapi/psc/threathunter/__init__.py
cbapi/psc/threathunter/models.py
cbapi/psc/threathunter/query.py
cbapi/psc/threathunter/rest_api.py
cbapi/psc/threathunter/models/binary.yaml
cbapi/psc/threathunter/models/feed.yaml
cbapi/psc/threathunter/models/ioc_v2.yaml
cbapi/psc/threathunter/models/iocs.yaml
cbapi/psc/threathunter/models/report.yaml
cbapi/psc/threathunter/models/report_severity.yaml
cbapi/psc/threathunter/models/watchlist.yaml
cbapi/response/__init__.py
cbapi/response/cblr.py
cbapi/response/event.py
cbapi/response/models.py
cbapi/response/query.py
cbapi/response/rest_api.py
cbapi_patched-1.7.5.dist-info/LICENSE
cbapi_patched-1.7.5.dist-info/METADATA
cbapi_patched-1.7.5.dist-info/WHEEL
cbapi_patched-1.7.5.dist-info/top_level.txt
cbapi_patched-1.7.5.dist-info/RECORD
